DFSNBA_TeamBuilder-0.0.2.dist-info/METADATA
DFSNBA_TeamBuilder-0.0.2.dist-info/RECORD
DFSNBA_TeamBuilder-0.0.2.dist-info/WHEEL
DFSNBA_TeamBuilder-0.0.2.dist-info/top_level.txt
DFS_NBA_Team_Builder/DK_Optimization_Function.py
DFS_NBA_Team_Builder/DK_TeamBuilder.py
DFS_NBA_Team_Builder/__init__.py
