Metadata-Version: 2.1
Name: DFSNBA-TeamBuilder
Version: 0.0.2
Summary: This package is used for creating draftkings lineups
Home-page: https://github.com/Blex42/DFS_NBA_Team_Builder
Author: Blex42
Author-email: blextechguides@gmail.com
License: UNKNOWN
Platform: UNKNOWN
Classifier: Programming Language :: Python :: 3
Classifier: License :: OSI Approved :: MIT License
Classifier: Operating System :: OS Independent
Requires-Dist: pandas
Requires-Dist: numpy
Requires-Dist: PuLP
